patriotlib/__init__.py
patriotlib/crypto.py
patriotlib/interfaces.py
patriotlib/keyexchange.py
patriotlib/metrics.py
patriotlib/replay_protection.py
patriotlib/replay_registry.py
patriotlib/rsa.py
patriotlib/signature.py
patriotlib/utils.py
patriotlib/replay_protection/__init__.py
patriotlib/replay_protection/memory_async.py
patriotlib/replay_protection/redis.py
patriotlib-0.1.3.dist-info/licenses/LICENSE
patriotlib-0.1.3.dist-info/METADATA
patriotlib-0.1.3.dist-info/WHEEL
patriotlib-0.1.3.dist-info/top_level.txt
patriotlib-0.1.3.dist-info/RECORD
