Metadata-Version: 2.4
Name: patriotlib
Version: 0.1.3
Summary: Secure encryption/signature library for client-server systems
Author: Your Name
License: MIT
Classifier: Programming Language :: Python :: 3
Classifier: License :: OSI Approved :: MIT License
Classifier: Operating System :: OS Independent
Requires-Python: >=3.8
License-File: LICENSE
Requires-Dist: cryptography>=41.0.0
Requires-Dist: redis>=4.2.0
Provides-Extra: dev
Requires-Dist: pytest; extra == "dev"
Dynamic: license-file
